{
    "type": "FeatureCollection",
    "features": [
        {
            "id": "meissen",
            "type": "Feature",
            "geometry": {
                "coordinates": [
                    13.4702,
                    51.1613
                ],
                "type": "Point"
            }
            "properties": {
                "preferredName": {
                    "label": "Meißen",
                    "language": "de"
                },
                "currentAffiliation": {
                    "country": "Germany",
                    "state": "Saxony"
                }
            }
        }
    ]
}